{
  "unversionedId": "JS/module/commonjs",
  "id": "JS/module/commonjs",
  "title": "CommonJS",
  "description": "CommonJS 规范主要用于服务器端模块化代码组织",
  "source": "@site/docs/03-JS/05-module/01-commonjs.md",
  "sourceDirName": "03-JS/05-module",
  "slug": "/JS/module/commonjs",
  "permalink": "/docs/JS/module/commonjs",
  "draft": false,
  "editUrl": "https://github.com/facebook/docusaurus/tree/main/packages/create-docusaurus/templates/shared/docs/03-JS/05-module/01-commonjs.md",
  "tags": [],
  "version": "current",
  "sidebarPosition": 1,
  "frontMatter": {},
  "sidebar": "tutorialSidebar",
  "previous": {
    "title": "模块化",
    "permalink": "/docs/JS/module/"
  },
  "next": {
    "title": "AMD",
    "permalink": "/docs/JS/module/amd"
  }
}